Metadata-Version: 2.1
Name: print-pp
Version: 0.4
Summary: Additional tools for printing
Home-page: https://github.com/i27ae15/print_pp.git
Author: Andres Melendes
Author-email: andresruse18@gmail.com
License: MIT
Keywords: printing,print
Classifier: Development Status :: 3 - Alpha
Classifier: Intended Audience :: Developers
Classifier: Topic :: Software Development :: Build Tools
Classifier: License :: OSI Approved :: MIT License
Classifier: Programming Language :: Python :: 3.8
Classifier: Programming Language :: Python :: 3.10
License-File: LICENSE.txt
